aliyunsdklinkwan/__init__.py
aliyunsdklinkwan/endpoint.py
aliyunsdklinkwan/request/__init__.py
aliyunsdklinkwan/request/v20190301/AcceptJoinPermissionAuthOrderRequest.py
aliyunsdklinkwan/request/v20190301/AddNodeToGroupRequest.py
aliyunsdklinkwan/request/v20190301/ApplyRoamingJoinPermissionRequest.py
aliyunsdklinkwan/request/v20190301/BindJoinPermissionToNodeGroupRequest.py
aliyunsdklinkwan/request/v20190301/CancelJoinPermissionAuthOrderRequest.py
aliyunsdklinkwan/request/v20190301/CheckCloudProductOpenStatusRequest.py
aliyunsdklinkwan/request/v20190301/CheckUserChargeStatusRequest.py
aliyunsdklinkwan/request/v20190301/CountGatewayTupleOrdersRequest.py
aliyunsdklinkwan/request/v20190301/CountGatewaysRequest.py
aliyunsdklinkwan/request/v20190301/CountNodeGroupsRequest.py
aliyunsdklinkwan/request/v20190301/CountNodeTupleOrdersRequest.py
aliyunsdklinkwan/request/v20190301/CountNodesByNodeGroupIdRequest.py
aliyunsdklinkwan/request/v20190301/CountNodesByOwnedJoinPermissionIdRequest.py
aliyunsdklinkwan/request/v20190301/CountNotificationsRequest.py
aliyunsdklinkwan/request/v20190301/CountOwnedJoinPermissionsRequest.py
aliyunsdklinkwan/request/v20190301/CountRentedJoinPermissionsRequest.py
aliyunsdklinkwan/request/v20190301/CreateCustomLocalJoinPermissionRequest.py
aliyunsdklinkwan/request/v20190301/CreateGatewayRequest.py
aliyunsdklinkwan/request/v20190301/CreateLocalJoinPermissionRequest.py
aliyunsdklinkwan/request/v20190301/CreateNodeGroupRequest.py
aliyunsdklinkwan/request/v20190301/DeleteGatewayRequest.py
aliyunsdklinkwan/request/v20190301/DeleteLocalJoinPermissionRequest.py
aliyunsdklinkwan/request/v20190301/DeleteNodeGroupRequest.py
aliyunsdklinkwan/request/v20190301/DescribeRegionsRequest.py
aliyunsdklinkwan/request/v20190301/GetFreqBandPlanGroupRequest.py
aliyunsdklinkwan/request/v20190301/GetGatewayPacketStatRequest.py
aliyunsdklinkwan/request/v20190301/GetGatewayRequest.py
aliyunsdklinkwan/request/v20190301/GetGatewayStatusStatRequest.py
aliyun_python_sdk_linkwan-1.0.4.dist-info/LICENSE
aliyun_python_sdk_linkwan-1.0.4.dist-info/METADATA
aliyun_python_sdk_linkwan-1.0.4.dist-info/WHEEL
aliyun_python_sdk_linkwan-1.0.4.dist-info/top_level.txt
aliyun_python_sdk_linkwan-1.0.4.dist-info/RECORD
